aitocoder/__init__.py
aitocoder/i18n/__init__.py
aitocoder/i18n/messages.py
aitocoder/repl_entry.py
autocoder/__init__.py
autocoder/agent/__init__.py
autocoder/agent/auto_demand_organizer.py
autocoder/agent/auto_filegroup.py
autocoder/agent/auto_guess_query.py
autocoder/agent/auto_learn.py
autocoder/agent/auto_learn_from_commit.py
autocoder/agent/auto_review_commit.py
autocoder/agent/auto_tool.py
autocoder/agent/base_agentic/__init__.py
autocoder/agent/base_agentic/agent_hub.py
autocoder/agent/base_agentic/agentic_lang.py
autocoder/agent/base_agentic/agentic_tool_display.py
autocoder/agent/base_agentic/base_agent.py
autocoder/agent/base_agentic/default_tools.py
autocoder/agent/base_agentic/test_base_agent.py
autocoder/agent/base_agentic/tool_registry.py
autocoder/agent/base_agentic/tools/__init__.py
autocoder/agent/base_agentic/tools/ask_followup_question_tool_resolver.py
autocoder/agent/base_agentic/tools/attempt_completion_tool_resolver.py
autocoder/agent/base_agentic/tools/base_tool_resolver.py
autocoder/agent/base_agentic/tools/example_tool_resolver.py
autocoder/agent/base_agentic/tools/execute_command_tool_resolver.py
autocoder/agent/base_agentic/tools/list_files_tool_resolver.py
autocoder/agent/base_agentic/tools/plan_mode_respond_tool_resolver.py
autocoder/agent/base_agentic/tools/read_file_tool_resolver.py
autocoder/agent/base_agentic/tools/replace_in_file_tool_resolver.py
autocoder/agent/base_agentic/tools/search_files_tool_resolver.py
autocoder/agent/base_agentic/tools/talk_to_group_tool_resolver.py
autocoder/agent/base_agentic/tools/talk_to_tool_resolver.py
autocoder/agent/base_agentic/tools/use_mcp_tool_resolver.py
autocoder/agent/base_agentic/tools/write_to_file_tool_resolver.py
autocoder/agent/base_agentic/types.py
autocoder/agent/base_agentic/utils.py
autocoder/agent/coder.py
autocoder/agent/designer.py
autocoder/agent/entry_command_agent/__init__.py
autocoder/agent/entry_command_agent/auto_tool.py
autocoder/agent/entry_command_agent/chat.py
aitocoder-0.3.0.dist-info/WHEEL
aitocoder-0.3.0.dist-info/entry_points.txt
aitocoder-0.3.0.dist-info/METADATA
aitocoder-0.3.0.dist-info/RECORD
